LanggraphMemory/__init__.py
LanggraphMemory/brain.py
LanggraphMemory/dbs.py
LanggraphMemory/llm.py
LanggraphMemory/orchestrators.py
LanggraphMemory/prompts.py
LanggraphMemory/states.py
LanggraphMemory/vectorDB.py
LanggraphMemory/workers.py
lengmem-1.0.2.dist-info/METADATA
lengmem-1.0.2.dist-info/WHEEL
lengmem-1.0.2.dist-info/entry_points.txt
lengmem-1.0.2.dist-info/RECORD
