Metadata-Version: 2.4
Name: LengMem
Version: 1.0.2
Summary: Layered Memory Architecture for LLM Agents with LangGraph
Requires-Python: >=3.11
Requires-Dist: aiofiles>=23.0.0
Requires-Dist: chromadb>=0.4.0
Requires-Dist: httpx>=0.25.0
Requires-Dist: langchain-community>=0.3.0
Requires-Dist: langchain-core>=0.3.0
Requires-Dist: langchain-milvus>=0.2.1
Requires-Dist: langchain-openai>=0.2.0
Requires-Dist: langchain>=0.3.0
Requires-Dist: langgraph-cli[inmem]>=0.1.0
Requires-Dist: langgraph>=0.4.0
Requires-Dist: lanngraph-wave-orchestrator>=1.1.7
Requires-Dist: openai>=1.0.0
Requires-Dist: pydantic>=2.0.0
Requires-Dist: python-dotenv>=1.0.0
Requires-Dist: sentence-transformers>=3.0.0
Requires-Dist: typing-extensions>=4.8.0
Provides-Extra: dev
Requires-Dist: black>=23.0.0; extra == 'dev'
Requires-Dist: langgraph-cli[inmem]>=0.1.0; extra == 'dev'
Requires-Dist: mypy>=1.5.0; extra == 'dev'
Requires-Dist: pytest-asyncio>=0.21.0; extra == 'dev'
Requires-Dist: pytest>=7.0.0; extra == 'dev'
Requires-Dist: ruff>=0.1.0; extra == 'dev'
Provides-Extra: production
Requires-Dist: alembic>=1.12.0; extra == 'production'
Requires-Dist: neo4j>=5.0.0; extra == 'production'
Requires-Dist: prometheus-client>=0.17.0; extra == 'production'
Requires-Dist: sqlalchemy>=2.0.0; extra == 'production'
Requires-Dist: structlog>=23.0.0; extra == 'production'
